azureml/__init__.py
azureml/contrib/__init__.py
azureml/contrib/notebook/__init__.py
azureml/contrib/notebook/_azureml_appinsights_handler.py
azureml/contrib/notebook/_azureml_handler.py
azureml/contrib/notebook/_cli_run_notebook_handler.py
azureml/contrib/notebook/_constants.py
azureml/contrib/notebook/_notebook_handler.py
azureml/contrib/notebook/_notebook_run_config.py
azureml/contrib/notebook/_notebook_runner_step.py
azureml/contrib/notebook/_papermill_deprecated_handler.py
azureml/contrib/notebook/extension.py
azureml/contrib/notebook/_engines/__init__.py
azureml/contrib/notebook/_engines/_utils.py
azureml/contrib/notebook/_engines/azureml_applicationinsights_engine.py
azureml/contrib/notebook/_engines/azureml_engine.py
azureml/contrib/notebook/_handlers/__init__.py
azureml/contrib/notebook/_handlers/cli_run_notebook_script.py
azureml/contrib/notebook/_handlers/papermill_notebook_run_handler.py
azureml/contrib/notebook/_scripts/kernel.js
azureml_contrib_notebook-1.60.0.data/data/etc/jupyter/nbconfig/notebook.d/azureml_contrib_notebook.json
azureml_contrib_notebook-1.60.0.data/data/share/jupyter/nbextensions/azureml/kernel.js
azureml_contrib_notebook-1.60.0.dist-info/licenses/LICENSE.txt
azureml_contrib_notebook-1.60.0.dist-info/METADATA
azureml_contrib_notebook-1.60.0.dist-info/WHEEL
azureml_contrib_notebook-1.60.0.dist-info/top_level.txt
azureml_contrib_notebook-1.60.0.dist-info/RECORD
